LICENSE
README.md
setup.py
thinkpad-tools
thinkpad_tools.egg-info/PKG-INFO
thinkpad_tools.egg-info/SOURCES.txt
thinkpad_tools.egg-info/dependency_links.txt
thinkpad_tools.egg-info/not-zip-safe
thinkpad_tools.egg-info/top_level.txt
thinkpad_tools_assets/__init__.py
thinkpad_tools_assets/__main__.py
thinkpad_tools_assets/battery.py
thinkpad_tools_assets/classes.py
thinkpad_tools_assets/cmd.py
thinkpad_tools_assets/persistence.py
thinkpad_tools_assets/thinkpad-tools.ini
thinkpad_tools_assets/thinkpad-tools.service
thinkpad_tools_assets/trackpoint.py
thinkpad_tools_assets/undervolt.py
thinkpad_tools_assets/utils.py