Metadata-Version: 1.2
Name: thinkpad-tools
Version: 0.13
Summary: Tools for ThinkPads
Home-page: UNKNOWN
Maintainer: Dev Singh
Maintainer-email: dev@singhk.dev
License: GPLv3
Project-URL: Bug Tracker, https://github.com/devksingh4/thinkpad-tools/issues
Project-URL: Documentation, https://github.com/devksingh4/thinkpad-tools/blob/master/README.md
Project-URL: Source Code, https://github.com/devksingh4/thinkpad-tools/
Keywords: thinkpad trackpoint battery undervolt
Platform: Linux
